README.md
setup.cfg
setup.py
sardana_streams/__init__.py
sardana_streams/client.py
sardana_streams/redis.py
sardana_streams.egg-info/PKG-INFO
sardana_streams.egg-info/SOURCES.txt
sardana_streams.egg-info/dependency_links.txt
sardana_streams.egg-info/requires.txt
sardana_streams.egg-info/top_level.txt
sardana_streams/recorder/__init__.py
sardana_streams/recorder/recorder.py
sardana_streams/recorder/scan.py