Metadata-Version: 2.1
Name: sardana-streams
Version: 0.1.0
Summary: Distributed sardana recorder
Home-page: http://github.com/ALBA-Synchrotron/sardana-streams
Author: Jose Tiago Macara Coutinho
Author-email: coutinhotiago@gmail.com
License: GPLv3
Project-URL: Documentation, https://github.com/ALBA-Synchrotron/sardana-streams
Project-URL: Source, https://github.com/ALBA-Synchrotron/sardana-streams
Platform: UNKNOWN
Classifier: Development Status :: 2 - Pre-Alpha
Classifier: Intended Audience :: Developers
Classifier: Natural Language :: English
Classifier: Programming Language :: Python :: 3
Classifier: Programming Language :: Python :: 3.5
Classifier: Programming Language :: Python :: 3.6
Classifier: Programming Language :: Python :: 3.7
Classifier: Programming Language :: Python :: 3.8
Classifier: Programming Language :: Python :: 3.9
Classifier: License :: OSI Approved :: GNU General Public License v3 (GPLv3)
Requires-Python: >=3.5
